lsnotes/.lsnotes
lsnotes/__init__.py
lsnotes/main.py
lsnotes-1.0.0.dist-info/LICENSE
lsnotes-1.0.0.dist-info/METADATA
lsnotes-1.0.0.dist-info/WHEEL
lsnotes-1.0.0.dist-info/entry_points.txt
lsnotes-1.0.0.dist-info/RECORD
