Metadata-Version: 2.1
Name: lsnotes
Version: 1.0.0
Summary: A simple tool to add descriptions to directories by creating .lsnotes files, with endless possibilities for customization.
License: MIT
Author: Louis Aeilot
Author-email: 1329415023@qq.com
Requires-Python: >=3.9,<4.0
Classifier: License :: OSI Approved :: MIT License
Classifier: Programming Language :: Python :: 3
Classifier: Programming Language :: Python :: 3.9
Classifier: Programming Language :: Python :: 3.10
Classifier: Programming Language :: Python :: 3.11
Classifier: Programming Language :: Python :: 3.12
Requires-Dist: typer (>=0.16.0,<0.17.0)
